pydoas/__init__.py
pydoas/_version.py
pydoas/analysis.py
pydoas/dataimport.py
pydoas/helpers.py
pydoas/inout.py
pydoas/data/import_info.txt
pydoas/data/doasis_resultfiles/D130909_S0636_i26_f36_r37_f01so2.dat
pydoas/data/doasis_resultfiles/D130909_S0636_i26_f36_r37_f02so2.dat
pydoas/data/doasis_resultfiles/D130909_S0636_i26_f36_r37_f03so2.dat
pydoas/data/doasis_resultfiles/D130909_S0636_i26_f36_r37_f04bro.dat
pydoas/data/doasis_resultfiles/D130909_S0756_i46_f56_r57_f01so2.dat
pydoas/data/doasis_resultfiles/D130909_S0756_i46_f56_r57_f02so2.dat
pydoas/data/doasis_resultfiles/D130909_S0756_i46_f56_r57_f03so2.dat
pydoas/data/doasis_resultfiles/D130909_S0756_i46_f56_r57_f04bro.dat
pydoas/data/fake_resultfiles/fake_result_file_fit1.csv
pydoas/data/fake_resultfiles/fake_result_file_fit2.csv
pydoas-2.1.0.dist-info/licenses/LICENSE
pydoas-2.1.0.dist-info/METADATA
pydoas-2.1.0.dist-info/WHEEL
pydoas-2.1.0.dist-info/top_level.txt
pydoas-2.1.0.dist-info/RECORD
