Metadata-Version: 2.4
Name: pydoas
Version: 2.1.0
Summary: A Python toolbox for post-analysis of DOAS (Differential Optical Absorption Spectroscopy) results
Author-email: Jonas Gliss <jonasgliss@gmail.com>
License: BSD-3-Clause
Project-URL: Homepage, https://github.com/jgliss/pydoas
Project-URL: Documentation, https://pydoas.readthedocs.io
Classifier: Development Status :: 5 - Production/Stable
Classifier: Intended Audience :: Science/Research
Classifier: Intended Audience :: Education
Classifier: Programming Language :: Python :: 3.9
Classifier: Programming Language :: Python :: 3.10
Classifier: Programming Language :: Python :: 3.11
Classifier: Programming Language :: Python :: 3.12
Classifier: Programming Language :: Python :: 3.13
Requires-Python: >=3.9
License-File: LICENSE
Requires-Dist: numpy
Requires-Dist: pandas
Requires-Dist: matplotlib
Dynamic: license-file
